Superfactorial/__init__.py
Superfactorial/function.py
superfactorial-0.0.2.dist-info/METADATA
superfactorial-0.0.2.dist-info/WHEEL
superfactorial-0.0.2.dist-info/top_level.txt
superfactorial-0.0.2.dist-info/RECORD
