Metadata-Version: 2.4
Name: Superfactorial
Version: 0.0.2
Summary: SUPERFACTORIAL
Author: Vaishnavi B
Author-email: baratamvaishnavisklm@gmail.com
Classifier: Development Status :: 1 - Planning
Classifier: Intended Audience :: Developers
Classifier: Programming Language :: Python :: 3
Classifier: Operating System :: Unix
Classifier: Operating System :: MacOS :: MacOS X
Classifier: Operating System :: Microsoft :: Windows
Dynamic: author
Dynamic: author-email
Dynamic: classifier
Dynamic: description
Dynamic: summary
